docs/Makefile
docs/source/conf.py
docs/source/index.rst
docs/source/modules.rst
docs/source/pytket.phir.rebasing.rst
docs/source/pytket.phir.rst
docs/source/pytket.phir.sharding.rst
pytket/phir/__init__.py
pytket/phir/api.py
pytket/phir/cli.py
pytket/phir/machine.py
pytket/phir/phirgen.py
pytket/phir/phirgen_parallel.py
pytket/phir/place_and_route.py
pytket/phir/placement.py
pytket/phir/py.typed
pytket/phir/qtm_machine.py
pytket/phir/routing.py
pytket/phir/rebasing/__init__.py
pytket/phir/rebasing/rebaser.py
pytket/phir/sharding/__init__.py
pytket/phir/sharding/shard.py
pytket/phir/sharding/sharder.py
pytket/phir/sharding/shards2ops.py
pytket_phir-0.10.1.dist-info/licenses/LICENSE
tests/__init__.py
tests/e2e_test.py
tests/test_api.py
tests/test_parallel_tk2.py
tests/test_parallelization.py
tests/test_phirgen.py
tests/test_placement.py
tests/test_rebaser.py
tests/test_sharder.py
tests/test_utils.py
tests/test_wasm.py
tests/data/qasm/arbitrary_qreg_names.qasm
tests/data/qasm/baby.qasm
tests/data/qasm/baby_with_rollup.qasm
tests/data/qasm/barrier_complex.qasm
tests/data/qasm/big_gate.qasm
tests/data/qasm/bv_n10.qasm
tests/data/qasm/classical0.qasm
tests/data/qasm/classical1.qasm
tests/data/qasm/classical_hazards.qasm
tests/data/qasm/classical_ordering.qasm
tests/data/qasm/cond_1.qasm
tests/data/qasm/cond_barrier.qasm
tests/data/qasm/cond_classical.qasm
tests/data/qasm/exec_order_two_qubits.qasm
tests/data/qasm/eztest.qasm
tests/data/qasm/group_ordering.qasm
tests/data/qasm/n10_test.qasm
tests/data/qasm/oned_brickwork_circuit_n20.qasm
tests/data/qasm/parallelization_test.qasm
tests/data/qasm/qv20_0.qasm
tests/data/qasm/rxrz.qasm
tests/data/qasm/simple.qasm
tests/data/qasm/simple_cond.qasm
tests/data/qasm/single_qubit_parallel_test.qasm
tests/data/qasm/sleep.qasm
tests/data/qasm/tk2_diff_angles.qasm
tests/data/qasm/tk2_same_angle.qasm
tests/data/wasm/add.wat
tests/data/wasm/testfile.wat
pytket_phir-0.10.1.dist-info/METADATA
pytket_phir-0.10.1.dist-info/WHEEL
pytket_phir-0.10.1.dist-info/entry_points.txt
pytket_phir-0.10.1.dist-info/top_level.txt
pytket_phir-0.10.1.dist-info/RECORD
