Metadata-Version: 2.4
Name: pytket-phir
Version: 0.10.1
Summary: A circuit analyzer and translator from pytket to PHIR
Author: Quantinuum
Maintainer-email: Kartik Singhal <Kartik.Singhal@quantinuum.com>
License: BSD 3-Clause License
Project-URL: Changelog, https://github.com/quantinuum/pytket-phir/blob/main/CHANGELOG.md
Project-URL: Documentation, https://quantinuum.github.io/pytket-phir/
Project-URL: Repository, https://github.com/quantinuum/pytket-phir.git
Classifier: Environment :: Console
Classifier: Intended Audience :: Developers
Classifier: Intended Audience :: Science/Research
Classifier: License :: OSI Approved :: BSD License
Classifier: Operating System :: OS Independent
Classifier: Programming Language :: Python :: 3
Classifier: Topic :: Scientific/Engineering
Classifier: Topic :: Software Development :: Libraries :: Python Modules
Classifier: Typing :: Typed
Requires-Python: <3.15,>=3.10
License-File: LICENSE
Requires-Dist: phir>=0.3.3
Requires-Dist: pytket>=2.0.0
Requires-Dist: wasmtime>=29.0.0
Provides-Extra: phirc
Requires-Dist: projectq>=0.8.0; extra == "phirc"
Requires-Dist: quantum-pecos>=0.6.0.dev2; extra == "phirc"
Dynamic: license-file
